silgeai/__init__.py
silgeai/demo.py
silgeai/dictPrint.py
silgeai/folderAnalysis.py
silgeai/test.py
silgeai/api/__init__.py
silgeai/api/asrapi.py
silgeai/api/getauth.py
silgeai/api/test.py
silgeai-1.3.3.dist-info/LICENSE
silgeai-1.3.3.dist-info/METADATA
silgeai-1.3.3.dist-info/WHEEL
silgeai-1.3.3.dist-info/top_level.txt
silgeai-1.3.3.dist-info/RECORD
