Metadata-Version: 2.1
Name: silgeai
Version: 1.3.3
Summary: 洞墟科技有限公司AI产品SDK
Home-page: http://github.com/yourusername/my_package
Author: WhiteCome
Author-email: waitKey1@outlook.com
License: MIT
Platform: UNKNOWN
License-File: LICENSE
Requires-Dist: websockets
Requires-Dist: requests
